aiorun.py
graingert_aiorun-2018.9.1.dist-info/LICENSE
graingert_aiorun-2018.9.1.dist-info/WHEEL
graingert_aiorun-2018.9.1.dist-info/METADATA
graingert_aiorun-2018.9.1.dist-info/RECORD
