Metadata-Version: 2.1
Name: graingert-aiorun
Version: 2018.9.1
Summary: Boilerplate for asyncio applications
Home-page: https://github.com/cjrh/aiorun
License: UNKNOWN
Author: Caleb Hattingh
Author-email: caleb.hattingh@gmail.com
Classifier: License :: OSI Approved :: Apache Software License
Classifier: Natural Language :: English
Classifier: Programming Language :: Python
Classifier: Programming Language :: Python :: 3.5
Classifier: Programming Language :: Python :: 3.6
Classifier: Programming Language :: Python :: 3.7
Classifier: Operating System :: OS Independent
Requires-Dist: typing; python_version < '3.5'
Requires-Dist: pytest; extra == "dev"
Requires-Dist: pytest-cov; extra == "dev"
Provides-Extra: dev
